creditutils/__init__.py
creditutils/apk_builder_util.py
creditutils/apk_util.py
creditutils/base_util.py
creditutils/dingtalk_util.py
creditutils/excel_util.py
creditutils/exec_cmd.py
creditutils/file_util.py
creditutils/git_util.py
creditutils/hash_util.py
creditutils/img_util.py
creditutils/mail_util.py
creditutils/net_util.py
creditutils/pipe_util.py
creditutils/png_util.py
creditutils/sftp_util.py
creditutils/str_enc_dec_util.py
creditutils/str_util.py
creditutils/svn_util.py
creditutils/system_util.py
creditutils/trivial_util.py
creditutils/zip_util.py
creditutils-0.3.2.dist-info/licenses/LICENSE
creditutils-0.3.2.dist-info/METADATA
creditutils-0.3.2.dist-info/WHEEL
creditutils-0.3.2.dist-info/top_level.txt
creditutils-0.3.2.dist-info/RECORD
