Metadata-Version: 2.4
Name: creditutils
Version: 0.3.2
Summary: python small tools util.
Home-page: https://github.com/pytxxy/creditutils
Author: liuzhy
Author-email: liuzhy@txxy.com
Project-URL: Bug Tracker, https://github.com/pytxxy/creditutils/issues
Classifier: Programming Language :: Python :: 3
Classifier: License :: OSI Approved :: MIT License
Classifier: Operating System :: OS Independent
Requires-Python: >=3.6
License-File: LICENSE
Requires-Dist: paramiko>=3.3.1
Requires-Dist: xmltodict>=0.11.0
Requires-Dist: chardet>=3.0.4
Requires-Dist: xlrd>=1.1.0
Requires-Dist: pypng>=0.0.18
Requires-Dist: GitPython>=3.1.11
Requires-Dist: Pillow>=6.0.0
Dynamic: license-file
